<annotation>
	<folder>3-1</folder>
	<filename>202106282023180006485.jpg</filename>
	<path>202106282023180006485.jpg</path>
	<source>
		<database />
		<annotation />
	</source>
	<size>
		<width>163</width>
		<height>178</height>
		<depth>3</depth>
	</size>
	<segmented>0</segmented>
	<object>
		<name>phone</name>
		<pose />
		<truncated>0</truncated>
		<difficult>0</difficult>
		<bndbox>
			<xmin>128</xmin>
			<ymin>61</ymin>
			<xmax>152</xmax>
			<ymax>76</ymax>
		</bndbox>
	</object>
	</annotation>